octave_kernel/__init__.py
octave_kernel/__main__.py
octave_kernel/_make_figures.m
octave_kernel/_version.py
octave_kernel/check.py
octave_kernel/kernel.json
octave_kernel/kernel.py
octave_kernel/@input/input.m
octave_kernel/@kbhit/kbhit.m
octave_kernel/@pause/pause.m
octave_kernel/@sleep/sleep.m
octave_kernel/@usleep/usleep.m
octave_kernel/@yes_or_no/yes_or_no.m
octave_kernel/images/logo-32x32.png
octave_kernel/images/logo-64x64.png
octave_kernel-0.35.1.data/data/share/jupyter/kernels/octave/kernel.json
octave_kernel-0.35.1.data/data/share/jupyter/kernels/octave/images/logo-32x32.png
octave_kernel-0.35.1.data/data/share/jupyter/kernels/octave/images/logo-64x64.png
octave_kernel-0.35.1.dist-info/METADATA
octave_kernel-0.35.1.dist-info/WHEEL
octave_kernel-0.35.1.dist-info/licenses/LICENSE.txt
octave_kernel-0.35.1.dist-info/RECORD
