Metadata-Version: 2.1
Name: octave_kernel
Version: 0.35.1
Summary: 'A Jupyter kernel for Octave.'
Project-URL: Homepage, http://github.com/Calysto/octave_kernel
Author-email: 'Steven Silvester' <steven.silvester@ieee.org>
License: Copyright (c) 2015-2019, Octave Kernel Development Team
License-File: LICENSE.txt
Classifier: Intended Audience :: Science/Research
Classifier: License :: OSI Approved :: BSD License
Classifier: Operating System :: OS Independent
Classifier: Programming Language :: Python
Classifier: Programming Language :: Python :: 3
Classifier: Topic :: Scientific/Engineering
Classifier: Topic :: Software Development
Classifier: Topic :: System :: Shells
Requires-Python: >=3.7
Requires-Dist: ipykernel
Requires-Dist: jupyter-client>=4.3.0
Requires-Dist: metakernel>=0.24.0
Provides-Extra: test
Requires-Dist: jupyter-kernel-test; extra == 'test'
Requires-Dist: nbconvert; extra == 'test'
Requires-Dist: pytest; extra == 'test'
